auroraview_mcp/__init__.py
auroraview_mcp/__main__.py
auroraview_mcp/connection.py
auroraview_mcp/discovery.py
auroraview_mcp/server.py
auroraview_mcp/resources/__init__.py
auroraview_mcp/resources/providers.py
auroraview_mcp/tools/__init__.py
auroraview_mcp/tools/api.py
auroraview_mcp/tools/dcc.py
auroraview_mcp/tools/debug.py
auroraview_mcp/tools/discovery.py
auroraview_mcp/tools/gallery.py
auroraview_mcp/tools/page.py
auroraview_mcp/tools/ui.py
auroraview_mcp-0.3.37.dist-info/METADATA
auroraview_mcp-0.3.37.dist-info/WHEEL
auroraview_mcp-0.3.37.dist-info/entry_points.txt
auroraview_mcp-0.3.37.dist-info/RECORD
