Metadata-Version: 2.4
Name: auroraview-mcp
Version: 0.3.37
Summary: MCP Server for AuroraView - AI-powered interaction with WebView applications
Project-URL: Homepage, https://github.com/loonghao/auroraview
Project-URL: Documentation, https://loonghao.github.io/auroraview/
Project-URL: Repository, https://github.com/loonghao/auroraview
Project-URL: Issues, https://github.com/loonghao/auroraview/issues
Author-email: AuroraView Team <hal.long@outlook.com>
License: MIT
Keywords: ai,auroraview,automation,dcc,mcp,webview
Classifier: Development Status :: 3 - Alpha
Classifier: Intended Audience :: Developers
Classifier: License :: OSI Approved :: MIT License
Classifier: Operating System :: OS Independent
Classifier: Programming Language :: Python :: 3
Classifier: Programming Language :: Python :: 3.10
Classifier: Programming Language :: Python :: 3.11
Classifier: Programming Language :: Python :: 3.12
Classifier: Topic :: Software Development :: Libraries :: Python Modules
Requires-Python: >=3.10
Requires-Dist: fastmcp>=2.0.0
Requires-Dist: httpx>=0.25.0
Requires-Dist: websockets>=12.0
Provides-Extra: dev
Requires-Dist: pytest-asyncio>=0.23; extra == 'dev'
Requires-Dist: pytest-cov>=4.0; extra == 'dev'
Requires-Dist: pytest>=8.0; extra == 'dev'
Requires-Dist: ruff>=0.8.0; extra == 'dev'
